{
  "schemaVersion": 1,
  "id": "l1nks-master-quest",
  "version": "${version}",
  "name": "L1nk's Master Quest",
  "description": "This mod adds the fabled Master Sword from the Legend of Zelda series into Minecraft, along with some other cool additions!",
  "authors": [
    "L1nkStrYk3r"
  ],
  "contact": {
    "homepage": "https://fabricmc.net/",
    "sources": "https://github.com/FabricMC/fabric-example-mod"
  },
  "license": "CC0-1.0",
  "icon": "assets/l1nks-master-quest/icon.png",
  "environment": "*",
  "entrypoints": {
    "main": [
      "net.l1nkstryk3r.mq.L1nksMasterQuest"
    ],
    "client": [
      "net.l1nkstryk3r.mq.L1nksMasterQuestClient"
    ],
    "fabric-datagen": [
      "net.l1nkstryk3r.mq.L1nksMasterQuestDataGenerator"
    ]
  },
  "mixins": [
    "l1nks-master-quest.mixins.json"
  ],
  "depends": {
    "fabricloader": ">=0.17.3",
    "minecraft": "~1.20.1",
    "java": ">=17",
    "fabric-api": "*"
  },
  "suggests": {
    "another-mod": "*"
  }
}